py_vectorbase_rest/__init__.py
py_vectorbase_rest/exceptions.py
py_vectorbase_rest/vectorbase_config.py
py_vectorbase_rest/vectorbase_rest.py
py_vectorbase_rest-0.1.2.dist-info/LICENSE
py_vectorbase_rest-0.1.2.dist-info/METADATA
py_vectorbase_rest-0.1.2.dist-info/WHEEL
py_vectorbase_rest-0.1.2.dist-info/top_level.txt
py_vectorbase_rest-0.1.2.dist-info/RECORD
